{
  "header": {
    "eyebrow": "Capital Matching Platform",
    "status": "Platform Connected",
    "statusDetail": "Current activity is synchronized across the platform."
  },
  "overviewStats": [
    {
      "label": "Opportunity pipelines",
      "value": "06",
      "trend": "Dashboard modules staged"
    },
    {
      "label": "Platform Connections",
      "value": "04",
      "trend": "Current data sources active"
    },
    {
      "label": "Data readiness",
      "value": "100%",
      "trend": "Environment placeholders defined"
    }
  ],
  "moduleCards": [
    {
      "title": "Deal ingestion",
      "description": "Prepare inbound opportunity records from spreadsheets, uploads, and partner feeds.",
      "accent": "blue"
    },
    {
      "title": "Participation tracking",
      "description": "Capture investor participation, commitment stages, and follow-up ownership.",
      "accent": "azure"
    },
    {
      "title": "Operations alerts",
      "description": "Route time-sensitive notifications from timers, webhooks, and workflow exceptions.",
      "accent": "green"
    }
  ]
}
